lifemanapy/__init__.py
lifemanapy/lifemanatibia.py
lifemanapy-0.0.20.dist-info/LICENSE
lifemanapy-0.0.20.dist-info/METADATA
lifemanapy-0.0.20.dist-info/WHEEL
lifemanapy-0.0.20.dist-info/top_level.txt
lifemanapy-0.0.20.dist-info/RECORD
